pytest_encode_kane/__init__.py
pytest_encode_kane/main.py
test/__init__.py
test/test_case.py
pytest_encode_kane-1.0.dist-info/METADATA
pytest_encode_kane-1.0.dist-info/WHEEL
pytest_encode_kane-1.0.dist-info/entry_points.txt
pytest_encode_kane-1.0.dist-info/top_level.txt
pytest_encode_kane-1.0.dist-info/RECORD
