Metadata-Version: 2.1
Name: pytest-encode-kane
Version: 1.0
Summary: set your encoding and logger
Home-page: https://gitee.com/yanxiaokang0904/pytest_encode_kane
Author: Kane.Yan
Author-email: 653847252@qq.com
License: proprietary
Keywords: pytest,py.test,pytest_encode_kane
Platform: UNKNOWN
Classifier: Framework :: Pytest
Classifier: Programming Language :: Python
Classifier: Topic :: Software Development :: Testing
Classifier: Programming Language :: Python :: 3.6
Requires-Dist: pytest
